<?xml version="1.0" encoding="utf-8" ?>
<dwsync>
<file name="Kiara.jpg" server="www.beyondthe100thmeridian.com" local="132191021169503464" remote="132206024390000000" Dst="1" />
<file name="Neo.jpg" server="www.beyondthe100thmeridian.com" local="132176246850805508" remote="132207740380000000" Dst="1" />
<file name="NeoAshley.jpg" server="www.beyondthe100thmeridian.com" local="132191021514019388" remote="132206024460000000" Dst="1" />
<file name="VictorE3_1.jpg" server="www.beyondthe100thmeridian.com" local="132191024903374228" remote="132206024480000000" Dst="1" />
<file name="VictorE3_2.jpg" server="www.beyondthe100thmeridian.com" local="132191025116495900" remote="132206024490000000" Dst="1" />
<file name="VictorLily.jpg" server="www.beyondthe100thmeridian.com" local="132191022839376463" remote="132206024530000000" Dst="1" />
<file name="VictorShark.jpg" server="www.beyondthe100thmeridian.com" local="132191021926077012" remote="132206024550000000" Dst="1" />
<file name="VB.png" server="www.beyondthe100thmeridian.com" local="132134063910000000" remote="132207740340000000" Dst="1" />
</dwsync>